README.md
requirements.txt
setup.cfg
setup.py
./src/timeNlp/resource/__init__.py
./src/timeNlp/resource/holi_lunar.json
./src/timeNlp/resource/holi_solar.json
./src/timeNlp/resource/reg.pkl
./src/timeNlp/resource/regex.txt
src/phone/__init__.py
src/phone/phone.py
src/ruleparse/__init__.py
src/ruleparse/cache.py
src/ruleparse/collections.py
src/ruleparse/exre.py
src/ruleparse/fmle.py
src/ruleparse/parsers.py
src/ruleparse/rules.py
src/ruleparse/skeleton.py
src/ruleparse/slots.py
src/ruleparse/time.py
src/ruleparse/utils.py
src/ruleparse.egg-info/PKG-INFO
src/ruleparse.egg-info/SOURCES.txt
src/ruleparse.egg-info/dependency_links.txt
src/ruleparse.egg-info/not-zip-safe
src/ruleparse.egg-info/requires.txt
src/ruleparse.egg-info/top_level.txt
src/timeNlp/LunarSolarConverter.py
src/timeNlp/RangeTimeEnum.py
src/timeNlp/StringPreHandler.py
src/timeNlp/Test.py
src/timeNlp/TimeNormalizer.py
src/timeNlp/TimePoint.py
src/timeNlp/TimeUnit.py
src/timeNlp/__init__.py
src/timeNlp/setup.py
src/timeNlp/resource/__init__.py
src/utils/__init__.py
src/utils/extractor.py
src/utils/money.py
src/utils/time.py