Metadata-Version: 2.1
Name: ruleparse
Version: 2020.1.17.2
Summary: 规则解析框架
Home-page: https://gitee.com/youfani/ruleparse
Author: niyoufa
Author-email: niyoufa@aegis-data.cn
License: mit
Project-URL: Documentation, https://gitee.com/youfani/ruleparse
Platform: any
Classifier: Development Status :: 4 - Beta
Classifier: Programming Language :: Python
Requires-Python: >=3.6
Provides-Extra: testing
